cloud_autopkg_runner/__init__.py
cloud_autopkg_runner/__main__.py
cloud_autopkg_runner/autopkg_prefs.py
cloud_autopkg_runner/config_loader.py
cloud_autopkg_runner/config_schema.py
cloud_autopkg_runner/exceptions.py
cloud_autopkg_runner/file_utils.py
cloud_autopkg_runner/git_client.py
cloud_autopkg_runner/logging_config.py
cloud_autopkg_runner/logging_context.py
cloud_autopkg_runner/metadata_cache.py
cloud_autopkg_runner/py.typed
cloud_autopkg_runner/recipe.py
cloud_autopkg_runner/recipe_finder.py
cloud_autopkg_runner/recipe_report.py
cloud_autopkg_runner/settings.py
cloud_autopkg_runner/shell.py
cloud_autopkg_runner/cache/__init__.py
cloud_autopkg_runner/cache/azure_blob_cache.py
cloud_autopkg_runner/cache/gcs_cache.py
cloud_autopkg_runner/cache/json_cache.py
cloud_autopkg_runner/cache/s3_cache.py
cloud_autopkg_runner/cache/sqlite_cache.py
cloud_autopkg_runner-0.25.1.dist-info/METADATA
cloud_autopkg_runner-0.25.1.dist-info/WHEEL
cloud_autopkg_runner-0.25.1.dist-info/entry_points.txt
cloud_autopkg_runner-0.25.1.dist-info/licenses/LICENSE.md
cloud_autopkg_runner-0.25.1.dist-info/RECORD
