Metadata-Version: 2.4
Name: cloud-autopkg-runner
Version: 0.25.1
Summary: A Python library designed to level-up your AutoPkg automations with a focus on CI/CD performance.
Project-URL: Homepage, https://github.com/MScottBlake/cloud-autopkg-runner
Project-URL: Documentation, https://github.com/MScottBlake/cloud-autopkg-runner/wiki
Project-URL: Repository, https://github.com/MScottBlake/cloud-autopkg-runner.git
Project-URL: Issues, https://github.com/MScottBlake/cloud-autopkg-runner/issues
Author-email: Scott Blake <mitchelsblake@gmail.com>
License-Expression: MIT
License-File: LICENSE.md
Keywords: autopkg
Classifier: Development Status :: 4 - Beta
Classifier: Intended Audience :: Developers
Classifier: Intended Audience :: Information Technology
Classifier: Intended Audience :: System Administrators
Classifier: License :: OSI Approved :: MIT License
Classifier: Operating System :: MacOS
Classifier: Operating System :: MacOS :: MacOS X
Classifier: Programming Language :: Python :: 3
Classifier: Programming Language :: Python :: 3.10
Classifier: Programming Language :: Python :: 3.11
Classifier: Programming Language :: Python :: 3.12
Classifier: Programming Language :: Python :: 3.13
Classifier: Programming Language :: Python :: 3.14
Classifier: Topic :: System :: Software Distribution
Classifier: Typing :: Typed
Requires-Python: >=3.10
Requires-Dist: pyyaml>=6.0.2
Requires-Dist: tomli>=2.3.0; python_version < '3.11'
Requires-Dist: xattr>=1.1.4
Provides-Extra: azure
Requires-Dist: azure-identity; extra == 'azure'
Requires-Dist: azure-storage-blob[aio]; extra == 'azure'
Provides-Extra: gcs
Requires-Dist: google-cloud-storage; extra == 'gcs'
Provides-Extra: json
Provides-Extra: s3
Requires-Dist: boto3; extra == 's3'
Provides-Extra: sqlite
